sdtg/__init__.py
sdtg/core.py
sdtg/exceptions.py
sdtg/models/__init__.py
sdtg/models/member.py
sdtg/models/tile.py
sdtg-1.1.3.dist-info/METADATA
sdtg-1.1.3.dist-info/WHEEL
sdtg-1.1.3.dist-info/top_level.txt
sdtg-1.1.3.dist-info/RECORD
