Metadata-Version: 2.1
Name: sdtg
Version: 1.1.3
Summary: Second-dimensional Telegram Games library.
Home-page: https://github.com/Vezono/sdtg-lib
Author: Vezono
Author-email: gbball.baas@gmail.com
License: UNKNOWN
Platform: UNKNOWN
Classifier: Programming Language :: Python :: 3
Classifier: License :: OSI Approved :: MIT License
Classifier: Operating System :: OS Independent
Requires-Python: >=3.6
